MANIFEST.in
README.rst
setup.py
markdown_embedimages.egg-info/PKG-INFO
markdown_embedimages.egg-info/SOURCES.txt
markdown_embedimages.egg-info/dependency_links.txt
markdown_embedimages.egg-info/not-zip-safe
markdown_embedimages.egg-info/requires.txt
markdown_embedimages.egg-info/top_level.txt
mei/__init__.py
mei/embed_images.py
mei/resources/README.rst
mei/resources/requirements.txt
mei/resources/version.txt