Metadata-Version: 1.0
Name: markdown-embedimages
Version: 0.1.4
Summary: A Mistune renderer that embeds images into the final document.
Home-page: UNKNOWN
Author: Dustin Oprea
Author-email: myselfasunder@gmail.com
License: UNKNOWN
Keywords: mistune markdown
Platform: UNKNOWN
